odoo/addons/mail_composer_cc_bcc_account/README.rst
odoo/addons/mail_composer_cc_bcc_account/__init__.py
odoo/addons/mail_composer_cc_bcc_account/__manifest__.py
odoo/addons/mail_composer_cc_bcc_account/i18n/it.po
odoo/addons/mail_composer_cc_bcc_account/i18n/mail_composer_cc_bcc_account.pot
odoo/addons/mail_composer_cc_bcc_account/models/__init__.py
odoo/addons/mail_composer_cc_bcc_account/models/mail_thread.py
odoo/addons/mail_composer_cc_bcc_account/readme/CONFIGURE.md
odoo/addons/mail_composer_cc_bcc_account/readme/CONTRIBUTORS.md
odoo/addons/mail_composer_cc_bcc_account/readme/CREDITS.md
odoo/addons/mail_composer_cc_bcc_account/readme/DESCRIPTION.md
odoo/addons/mail_composer_cc_bcc_account/readme/USAGE.md
odoo/addons/mail_composer_cc_bcc_account/static/description/icon.png
odoo/addons/mail_composer_cc_bcc_account/static/description/index.html
odoo/addons/mail_composer_cc_bcc_account/static/img/email_template_form_cc_bcc.png
odoo/addons/mail_composer_cc_bcc_account/static/img/mail_compose_message_default_cc_bcc.png
odoo/addons/mail_composer_cc_bcc_account/static/img/mail_compose_message_template_cc_bcc.png
odoo/addons/mail_composer_cc_bcc_account/static/img/res_company_form_default_cc_bcc.png
odoo/addons/mail_composer_cc_bcc_account/tests/__init__.py
odoo/addons/mail_composer_cc_bcc_account/tests/test_mail_cc_bcc.py
odoo/addons/mail_composer_cc_bcc_account/wizards/__init__.py
odoo/addons/mail_composer_cc_bcc_account/wizards/account_move_send.py
odoo/addons/mail_composer_cc_bcc_account/wizards/account_move_send.xml
odoo_addon_mail_composer_cc_bcc_account-17.0.1.0.1.dist-info/METADATA
odoo_addon_mail_composer_cc_bcc_account-17.0.1.0.1.dist-info/WHEEL
odoo_addon_mail_composer_cc_bcc_account-17.0.1.0.1.dist-info/top_level.txt
odoo_addon_mail_composer_cc_bcc_account-17.0.1.0.1.dist-info/RECORD
