Metadata-Version: 2.1
Name: odoo-addon-mail_composer_cc_bcc_account
Version: 17.0.1.0.1
Requires-Python: >=3.10
Requires-Dist: odoo-addon-mail_composer_cc_bcc>=17.0dev,<17.1dev
Requires-Dist: odoo>=17.0a,<17.1dev
Summary: This module enables sending mail to CC and BCC partners for invoices.
Home-page: https://github.com/OCA/social
License: AGPL-3
Author: Camptocamp SA, Odoo Community Association (OCA)
Author-email: support@odoo-community.org
Classifier: Programming Language :: Python
Classifier: Framework :: Odoo
Classifier: Framework :: Odoo :: 17.0
Classifier: License :: OSI Approved :: GNU Affero General Public License v3
Classifier: Development Status :: 3 - Alpha
